{
  "fileName": "Mario",
  "driverName": "MARIO",
  "driverCode": "MR",
  "voiceclipCount": 81,
  "elementCount": 81,
  "elements": [
    {
      "userFriendlyName": "DASH_S_1",
      "uName": "Kart64Mario02_07_Amb.ny.32.dspadpcm",
      "dxName": "pVO_MR_DSH_S",
      "bfwavFileSize": "19168",
      "checksumMD5": "d1f7607ac2add683c1128fc8ed6e35ad"
    },
    {
      "userFriendlyName": "TRICK_1",
      "uName": "Kart64Mario02_12_Amb.ny.32.dspadpcm",
      "dxName": "pVO_MR_JP_ACT",
      "bfwavFileSize": "27304",
      "checksumMD5": "585af3d9b0ee35ed0c80337d8d9abe8f"
    },
    {
      "userFriendlyName": "TRICK_2",
      "uName": "Kart64Mario03_04_Amb.ny.32.dspadpcm",
      "dxName": "pVO_MR_JP_ACT2",
      "bfwavFileSize": "28496",
      "checksumMD5": "fa2e14f7eaead9ce64fd44762efe3d01"
    },
    {
      "userFriendlyName": "DASH_1",
      "uName": "Kart64Mario03_06_Amb.ny.32.dspadpcm",
      "dxName": "pVO_MR_DSH",
      "bfwavFileSize": "23120",
      "checksumMD5": "f64d624630a7c53fa9c54c525f7e31b5"
    },
    {
      "userFriendlyName": "TRICK_3",
      "uName": "Kart64Mario04_01_PB_Amb.ny.32.dspadpcm",
      "dxName": "pVO_MR_JP_ACT_END",
      "bfwavFileSize": "22664",
      "checksumMD5": "130dfe1195e40fb697a0393931cfc4a2"
    },
    {
      "userFriendlyName": "SLIPSTREAM_1",
      "uName": "Kart64Mario04_09_amb.ny.32.dspadpcm",
      "dxName": "pVO_MR_STRM",
      "bfwavFileSize": "37952",
      "checksumMD5": "ec280f8de0258956b13bc1acd0f82b45"
    },
    {
      "userFriendlyName": "TRICK_SB_3",
      "uName": "Kart64Mario05_03_Amb.ny.32.dspadpcm",
      "dxName": "pVO_MR_JP_ACT_SB_END",
      "bfwavFileSize": "18184",
      "checksumMD5": "76ad398a70d79828cd567bb291227091"
    },
    {
      "userFriendlyName": "DASH_S_2",
      "uName": "Kart64Mario05_05_Amb.ny.32.dspadpcm",
      "dxName": "pVO_MR_DSH_S2",
      "bfwavFileSize": "21928",
      "checksumMD5": "6532b39a3b9fafc4eb0fe00db28cf79a"
    },
    {
      "userFriendlyName": "ANTI-GRAVITY_DASH_1",
      "uName": "Kart64Mario05_14_cut_Amb.ny.32.dspadpcm",
      "dxName": "pVO_MR_HOVER_DASH",
      "bfwavFileSize": "24424",
      "checksumMD5": "fbeaca3247d6f86f57ff6c009c3c183e"
    },
    {
      "userFriendlyName": "DASH_2",
      "uName": "Kart64Mario06_02_Amb.ny.32.dspadpcm",
      "dxName": "pVO_MR_DSH2",
      "bfwavFileSize": "25968",
      "checksumMD5": "5db3c9aaf159f6a00b5e504ea5570427"
    },
    {
      "userFriendlyName": "DASH_3",
      "uName": "Kart64Mario06_05_Amb.ny.32.dspadpcm",
      "dxName": "pVO_MR_DSH3",
      "bfwavFileSize": "26288",
      "checksumMD5": "57ebfc3c10fe65f7642b741858bfb22e"
    },
    {
      "userFriendlyName": "DASH_4",
      "uName": "Kart64Mario06_07_Amb.ny.32.dspadpcm",
      "dxName": "pVO_MR_DSH_END",
      "bfwavFileSize": "24032",
      "checksumMD5": "904fdc001d13c0800a2405e1bf3b45bc"
    },
    {
      "userFriendlyName": "DAMAGE_CRASH_1",
      "uName": "Kart64Mario10_02_Amb.ny.32.dspadpcm",
      "dxName": "pVO_MR_DMG_CRSH",
      "bfwavFileSize": "9960",
      "checksumMD5": "c1585154e2b50bcc91714d5dbc284643"
    },
    {
      "userFriendlyName": "DAMAGE_SPIN_1",
      "uName": "Kart64Mario10_03_Amb.ny.32.dspadpcm",
      "dxName": "pVO_MR_DMG_SPN",
      "bfwavFileSize": "21424",
      "checksumMD5": "ca39bf4dce0e81ffbfabc0e4168ed6b9"
    },
    {
      "userFriendlyName": "DAMAGE_CRASH_2",
      "uName": "Kart64Mario10_04_Amb.ny.32.dspadpcm",
      "dxName": "pVO_MR_DMG_CRSH_END",
      "bfwavFileSize": "17080",
      "checksumMD5": "6af88d620706c843efed87dffede4d06"
    },
    {
      "userFriendlyName": "FINISH_GOOD_1",
      "uName": "Kart64Mario14_Select4_Amb.ny.32.dspadpcm",
      "dxName": "pVO_MR_GOL_GOD",
      "bfwavFileSize": "36624",
      "checksumMD5": "b18879ef018c1c522c191e5c2a6427bd"
    },
    {
      "userFriendlyName": "FINISH_FIRST_1",
      "uName": "Kart64Mario14_Select5_Amb.ny.32.dspadpcm",
      "dxName": "pVO_MR_GOL_TOP",
      "bfwavFileSize": "18376",
      "checksumMD5": "6cb597c74be9369ef2ba9b0888c5a9e9"
    },
    {
      "userFriendlyName": "SLIPSTREAM_2",
      "uName": "Kart64Mario22_04_amb.ny.32.dspadpcm",
      "dxName": "pVO_MR_STRM2",
      "bfwavFileSize": "41888",
      "checksumMD5": "69cdb4e0e3f18e5ff45e6f05cf2adba1"
    },
    {
      "userFriendlyName": "OVERTAKE_1",
      "uName": "MA-RA-01_01_Amb.ny.32.c4.dspadpcm",
      "dxName": "pVO_MR_OVTAK",
      "bfwavFileSize": "14392",
      "checksumMD5": "093e088eeabd2013344646ac1a5d4390"
    },
    {
      "userFriendlyName": "OVERTAKE_2",
      "uName": "MA-RA-01_04_Amb.ny.32.c4.dspadpcm",
      "dxName": "pVO_MR_OVTAK2",
      "bfwavFileSize": "17584",
      "checksumMD5": "596bcfd44ae51344379ffe78ffe93749"
    },
    {
      "userFriendlyName": "OVERTAKE_3",
      "uName": "MA-RA-01_06_Amb.ny.32.c4.dspadpcm",
      "dxName": "pVO_MR_OVTAK3",
      "bfwavFileSize": "14392",
      "checksumMD5": "7476fd2c8a99e047ed3badfa0959c025"
    },
    {
      "userFriendlyName": "STALL_2",
      "uName": "MA-RD-01_14_Amb.ny.32.c4.dspadpcm",
      "dxName": "pVO_MR_STR_FAIL_END",
      "bfwavFileSize": "24552",
      "checksumMD5": "355e60769dad7c768260f98fcd61d10b"
    },
    {
      "userFriendlyName": "DAMAGE_BOUND_1",
      "uName": "MA-RD-02_03_Amb.ny.32.c4.dspadpcm",
      "dxName": "pVO_MR_DMG_BOUND",
      "bfwavFileSize": "3160",
      "checksumMD5": "c27ffe93f6d443f9ded7cde9e7df5473"
    },
    {
      "userFriendlyName": "ITEM_BLOOPER_1",
      "uName": "MA-RD-02_03_Amb.ny.32.c4.dspadpcm",
      "dxName": "pVO_MR_ITM_GESSO",
      "bfwavFileSize": "3160",
      "checksumMD5": "c27ffe93f6d443f9ded7cde9e7df5473"
    },
    {
      "userFriendlyName": "DAMAGE_BOUND_2",
      "uName": "MA-RD-02_10_Amb.ny.32.c4.dspadpcm",
      "dxName": "pVO_MR_DMG_BOUND_END",
      "bfwavFileSize": "3392",
      "checksumMD5": "0e7093b041a31df43b486d87e3038e50"
    },
    {
      "userFriendlyName": "ITEM_BLOOPER_2",
      "uName": "MA-RD-02_10_Amb.ny.32.c4.dspadpcm",
      "dxName": "pVO_MR_ITM_GESSO_END",
      "bfwavFileSize": "3392",
      "checksumMD5": "0e7093b041a31df43b486d87e3038e50"
    },
    {
      "userFriendlyName": "ITEM_PLACE_BEHIND_2",
      "uName": "MA-RI-01_02_Amb.ny.32.c4.dspadpcm",
      "dxName": "pVO_MR_ITM_PUT_END",
      "bfwavFileSize": "3464",
      "checksumMD5": "ac9c6f6cfba2739879f5d320a6c80173"
    },
    {
      "userFriendlyName": "ITEM_THROW_FORWARD_2",
      "uName": "MA-RI-02_08_Amb.ny.32.c4.dspadpcm",
      "dxName": "pVO_MR_ITM_TRW_END",
      "bfwavFileSize": "7848",
      "checksumMD5": "0d9a20bbf3e346d5f4fc7a6a8d04b45a"
    },
    {
      "userFriendlyName": "ITEM_HIT_SUCCESS_1",
      "uName": "MA-RI-03_03_Amb.ny.32.c4.dspadpcm",
      "dxName": "pVO_MR_ITM_SCES",
      "bfwavFileSize": "9312",
      "checksumMD5": "007983e31550c640f6ad7297fbc316af"
    },
    {
      "userFriendlyName": "ITEM_HIT_SUCCESS_3",
      "uName": "MA-RI-03_04_Amb.ny.32.c4.dspadpcm",
      "dxName": "pVO_MR_ITM_SCES_END",
      "bfwavFileSize": "10824",
      "checksumMD5": "4a1d18a21105a3e973a04dee49219e3e"
    },
    {
      "userFriendlyName": "ITEM_STAR_2",
      "uName": "MA-RI-04_07_Amb.ny.32.c4.dspadpcm",
      "dxName": "pVO_MR_ITM_STAR_END",
      "bfwavFileSize": "19152",
      "checksumMD5": "3f6c7120b9a1a32bb9daa77864278449"
    },
    {
      "userFriendlyName": "DAMAGE_SPIN_2",
      "uName": "Mario07ALim_00024_Amb.ny.32.c4.dspadpcm",
      "dxName": "pVO_MR_DMG_SPN_END",
      "bfwavFileSize": "18120",
      "checksumMD5": "4bc3371f124165cd08d9b28b30efee8c"
    },
    {
      "userFriendlyName": "SLIPSTREAM_3",
      "uName": "MarioA1Lim_05_12_Amb.ny.32.c4.dspadpcm",
      "dxName": "pVO_MR_STRM_END",
      "bfwavFileSize": "44600",
      "checksumMD5": "ff3103215a134694931cfadeaf36f7c7"
    },
    {
      "userFriendlyName": "STALL_1",
      "uName": "Mario_00055_Amb.ny.32.c4.dspadpcm",
      "dxName": "pVO_MR_STR_FAIL",
      "bfwavFileSize": "19296",
      "checksumMD5": "70d439ef14f81c810e6429c659eba0f0"
    },
    {
      "userFriendlyName": "DASH_S_3",
      "uName": "Mario_00090_40CDown_Amb.ny.32.c4.dspadpcm",
      "dxName": "pVO_MR_DSH_S3",
      "bfwavFileSize": "14696",
      "checksumMD5": "764bccfa7023a5aad3a4713b66e43a19"
    },
    {
      "userFriendlyName": "OVERTAKE_5",
      "uName": "mr_Action_Attack-03_Amb.ny.32.dspadpcm",
      "dxName": "pVO_MR_OVTAK_END",
      "bfwavFileSize": "7360",
      "checksumMD5": "a095f827177cdd08c37ff26870dc630e"
    },
    {
      "userFriendlyName": "DASH_S_4",
      "uName": "mr_Action_Dash-11_Amb.ny.32.dspadpcm",
      "dxName": "pVO_MR_DSH_S_END",
      "bfwavFileSize": "23064",
      "checksumMD5": "226a6727e327f78de8fb8c7db0a3dc33"
    },
    {
      "userFriendlyName": "ITEM_THROW_FORWARD_1",
      "uName": "mr_Action_Jump-10_Amb.ny.32.dspadpcm",
      "dxName": "pVO_MR_ITM_TRW",
      "bfwavFileSize": "11256",
      "checksumMD5": "4aaa534a776305a58413d922c4b4bca7"
    },
    {
      "userFriendlyName": "OVERTAKE_4",
      "uName": "mr_Action_Overtake-05_Amb.ny.32.dspadpcm",
      "dxName": "pVO_MR_OVTAK4",
      "bfwavFileSize": "18120",
      "checksumMD5": "09a9347597792f6c7384a73a310c177f"
    },
    {
      "userFriendlyName": "FINISH_FIRST_3",
      "uName": "mr_Action_RocketStart-01_Amb.ny.32.dspadpcm",
      "dxName": "pVO_MR_GOL_TOP_END",
      "bfwavFileSize": "31112",
      "checksumMD5": "6a780457ea41bed479af7d6a6495c4a0"
    },
    {
      "userFriendlyName": "FINISH_BAD_3",
      "uName": "mr_Damage_L-09_Amb.ny.32.dspadpcm",
      "dxName": "pVO_MR_GOL_BAD_END",
      "bfwavFileSize": "20880",
      "checksumMD5": "d079293106ab90d45e3af9dad8bcca03"
    },
    {
      "userFriendlyName": "DAMAGE_S_1",
      "uName": "mr_Damage_M-02_Amb.ny.32.dspadpcm",
      "dxName": "pVO_MR_DMG_S",
      "bfwavFileSize": "16888",
      "checksumMD5": "f5f18492d24ef18cf8057d035a71ae2e"
    },
    {
      "userFriendlyName": "DAMAGE_S_2",
      "uName": "mr_Damage_M-07_Amb.ny.32.dspadpcm",
      "dxName": "pVO_MR_DMG_S_END",
      "bfwavFileSize": "16800",
      "checksumMD5": "ea528f43ff3f968d75789b332478c430"
    },
    {
      "userFriendlyName": "FINISH_BAD_1",
      "uName": "mr_Goal_Rankout-03_Amb.ny.32.dspadpcm",
      "dxName": "pVO_MR_GOL_BAD",
      "bfwavFileSize": "30440",
      "checksumMD5": "c2230f8d1e52006b778633b268b5ed2a"
    },
    {
      "userFriendlyName": "FINISH_GOOD_3",
      "uName": "mr_Goal_Top-09_Amb.ny.32.dspadpcm",
      "dxName": "pVO_MR_GOL_GOD_END",
      "bfwavFileSize": "22432",
      "checksumMD5": "e5d2acaab4e7d5933e93459235737f54"
    },
    {
      "userFriendlyName": "ITEM_PLACE_BEHIND_1",
      "uName": "mr_Item_Put-04TS0.85_Amb.ny.32.dspadpcm",
      "dxName": "pVO_MR_ITM_PUT",
      "bfwavFileSize": "8752",
      "checksumMD5": "1829a670d7f8a0ff17030db47c4959b7"
    },
    {
      "userFriendlyName": "FINISH_BAD_2",
      "uName": "mr_Minigame_Gameover-4_6_Amb.ny.32.dspadpcm",
      "dxName": "pVO_MR_GOL_BAD2",
      "bfwavFileSize": "26000",
      "checksumMD5": "fc693ff2d4daed508a1141dc0a91d648"
    },
    {
      "userFriendlyName": "ITEM_STAR_1",
      "uName": "mr_Minigame_Start-04_Amb.ny.32.dspadpcm",
      "dxName": "pVO_MR_ITM_STAR",
      "bfwavFileSize": "33288",
      "checksumMD5": "617e037559570050b9192a832d77b2c7"
    },
    {
      "userFriendlyName": "FINISH_FIRST_2",
      "uName": "mr_Minigame_Win-05_Amb.ny.32.dspadpcm",
      "dxName": "pVO_MR_GOL_TOP2",
      "bfwavFileSize": "32952",
      "checksumMD5": "548771a73933ebf2416583e503fae1d6"
    },
    {
      "userFriendlyName": "ANTI-GRAVITY_SPIN_1",
      "uName": "MR_RA_CHOV_01_13_Amb.ny.32.dspadpcm",
      "dxName": "pVO_MR_HOVER_CHARGE",
      "bfwavFileSize": "12424",
      "checksumMD5": "a18c49642b6ed77c281bf8fa438c9f14"
    },
    {
      "userFriendlyName": "ANTI-GRAVITY_SPIN_2",
      "uName": "MR_RA_CHOV_02_03_Amb.ny.32.dspadpcm",
      "dxName": "pVO_MR_HOVER_CHARGE2",
      "bfwavFileSize": "12800",
      "checksumMD5": "a0ddaefea8ee0123a75eec217124d7c0"
    },
    {
      "userFriendlyName": "ANTI-GRAVITY_SPIN_3",
      "uName": "MR_RA_CHOV_02_14_Amb.ny.32.dspadpcm",
      "dxName": "pVO_MR_HOVER_CHARGE_END",
      "bfwavFileSize": "14112",
      "checksumMD5": "68a21b3995433f0d78914a59ac7d4d3f"
    },
    {
      "userFriendlyName": "START_GLIDE_3",
      "uName": "MR_RA_DHOV_01_01_60CUP_Amb.ny.32.dspadpcm",
      "dxName": "pVO_MR_START_GLIDE_END",
      "bfwavFileSize": "29264",
      "checksumMD5": "c38fce92ca9107e7ce7231499256257c"
    },
    {
      "userFriendlyName": "ANTI-GRAVITY_DASH_2",
      "uName": "MR_RA_DHOV_01_10_Amb.ny.32.dspadpcm",
      "dxName": "pVO_MR_HOVER_DASH2",
      "bfwavFileSize": "21704",
      "checksumMD5": "3b3762bdf639dff8b6460762326b5f52"
    },
    {
      "userFriendlyName": "START_GLIDE_2",
      "uName": "MR_RA_DHOV_2_2-2_1_PB_Amb.ny.32.dspadpcm",
      "dxName": "pVO_MR_START_GLIDE2",
      "bfwavFileSize": "33344",
      "checksumMD5": "9f6dd505e7d85aed423af1d16ae0c0df"
    },
    {
      "userFriendlyName": "ANTI-GRAVITY_DASH_3",
      "uName": "MR_RA_GLD_01_00_Amb.ny.32.dspadpcm",
      "dxName": "pVO_MR_HOVER_DASH_END",
      "bfwavFileSize": "21080",
      "checksumMD5": "b7bf7fd338dc09bc199c4579df15ea5e"
    },
    {
      "userFriendlyName": "START_GLIDE_1",
      "uName": "MR_RA_GLD_1_3-1_5_PB_Amb.ny.32.dspadpcm",
      "dxName": "pVO_MR_START_GLIDE",
      "bfwavFileSize": "25936",
      "checksumMD5": "eeee26a32bd15ffd28f8fc4e50399c88"
    },
    {
      "userFriendlyName": "ITEM_HIT_SUCCESS_2",
      "uName": "MR_RA_JUML_01_14_Amb.ny.32.dspadpcm",
      "dxName": "pVO_MR_ITM_SCES2",
      "bfwavFileSize": "13120",
      "checksumMD5": "be784efefcf1dc6b61a8c71e3019a846"
    },
    {
      "userFriendlyName": "TRICK_SA_1",
      "uName": "MR_RA_JUMS_01_11_Amb.ny.32.dspadpcm",
      "dxName": "pVO_MR_JP_ACT_SA",
      "bfwavFileSize": "11008",
      "checksumMD5": "d12f484d1c1d71f5f4fb81f6a0c562a6"
    },
    {
      "userFriendlyName": "TRICK_SA_2",
      "uName": "MR_RA_JUMS_01_15_Amb.ny.32.dspadpcm",
      "dxName": "pVO_MR_JP_ACT_SA2",
      "bfwavFileSize": "4536",
      "checksumMD5": "1cb3e9c76540935f87e05adb79b02f80"
    },
    {
      "userFriendlyName": "TRICK_SA_3",
      "uName": "MR_RA_JUMS_02_02_Amb.ny.32.dspadpcm",
      "dxName": "pVO_MR_JP_ACT_SA_END",
      "bfwavFileSize": "12744",
      "checksumMD5": "c3772e5105593405799c9b558e06efe0"
    },
    {
      "userFriendlyName": "TRICK_SB_1",
      "uName": "MR_RA_JUMS_02_03_Amb.ny.32.dspadpcm",
      "dxName": "pVO_MR_JP_ACT_SB",
      "bfwavFileSize": "13408",
      "checksumMD5": "e985dee959c558c75b04738f48c30893"
    },
    {
      "userFriendlyName": "TRICK_SB_2",
      "uName": "MR_RA_JUMS_02_09_Amb.ny.32.dspadpcm",
      "dxName": "pVO_MR_JP_ACT_SB2",
      "bfwavFileSize": "17016",
      "checksumMD5": "96443d4a20ed66923c1e94caf10001f2"
    },
    {
      "userFriendlyName": "START_ANTI-GRAVITY_1",
      "uName": "MR_RA_SHOV_02_04_Amb.ny.32.dspadpcm",
      "dxName": "pVO_MR_START_HOVER",
      "bfwavFileSize": "8768",
      "checksumMD5": "25e7f2a82a59bcbc12016ba4707a6a42"
    },
    {
      "userFriendlyName": "START_ANTI-GRAVITY_2",
      "uName": "MR_RA_SHOV_04_06_Amb.ny.32.dspadpcm",
      "dxName": "pVO_MR_START_HOVER2",
      "bfwavFileSize": "21728",
      "checksumMD5": "8f1530b2e41ca5b5766e5e3ea291f7d6"
    },
    {
      "userFriendlyName": "START_ANTI-GRAVITY_3",
      "uName": "MR_RA_SHOV_06_08_Amb.ny.32.dspadpcm",
      "dxName": "pVO_MR_START_HOVER_END",
      "bfwavFileSize": "12192",
      "checksumMD5": "ad60b92f6bebf41da4803502389e2b6f"
    },
    {
      "userFriendlyName": "RETRIEVED_FROM_LAVA_1",
      "uName": "MR_RD_CMBL_01_07_Amb.ny.32.dspadpcm",
      "dxName": "pVO_MR_CMB_LAVA",
      "bfwavFileSize": "19600",
      "checksumMD5": "11274c825beedebb96e09d447eb9a920"
    },
    {
      "userFriendlyName": "RETRIEVED_FROM_LAVA_2",
      "uName": "MR_RD_CMBL_1_10-1_9_Amb.ny.32.dspadpcm",
      "dxName": "pVO_MR_CMB_LAVA_END",
      "bfwavFileSize": "27088",
      "checksumMD5": "a16dde825f28585e9d1685063d8c1ab3"
    },
    {
      "userFriendlyName": "RETRIEVED_FROM_WATER_1",
      "uName": "MR_RD_CMBW_01_05_Amb.ny.32.dspadpcm",
      "dxName": "pVO_MR_CMB_WATER",
      "bfwavFileSize": "18592",
      "checksumMD5": "5a0dd81dc735498267122d2604c8d5a0"
    },
    {
      "userFriendlyName": "RETRIEVED_FROM_WATER_2",
      "uName": "MR_RD_CMBW_01_10_Amb.ny.32.dspadpcm",
      "dxName": "pVO_MR_CMB_WATER_END",
      "bfwavFileSize": "19032",
      "checksumMD5": "3f4dc4831c55eb39799a3d38364867ba"
    },
    {
      "userFriendlyName": "FALL_LAVA_1",
      "uName": "MR_RD_LAFA_01_00_short_Amb.ny.32.dspadpcm",
      "dxName": "pVO_MR_FALL_LAVA",
      "bfwavFileSize": "6384",
      "checksumMD5": "93f14937e40e492cec3dc27944560ef9"
    },
    {
      "userFriendlyName": "FALL_LAVA_2",
      "uName": "MR_RD_LAFA_01_09_cut_Amb.ny.32.dspadpcm",
      "dxName": "pVO_MR_FALL_LAVA_END",
      "bfwavFileSize": "6848",
      "checksumMD5": "a1a9259aeea31e4c9012c1bc1a4db0d4"
    },
    {
      "userFriendlyName": "FALL_SHORT_1",
      "uName": "MR_RD_SFAL_01_04_Amb.ny.32.dspadpcm",
      "dxName": "pVO_MR_FALL_SHORT",
      "bfwavFileSize": "6720",
      "checksumMD5": "b3d49fcc15214744c1431a82f5989450"
    },
    {
      "userFriendlyName": "FALL_SHORT_2",
      "uName": "MR_RD_SFAL_01_09_50CUP_Amb.ny.32.dspadpcm",
      "dxName": "pVO_MR_FALL_SHORT_END",
      "bfwavFileSize": "7064",
      "checksumMD5": "a9d0935008524885328a7a2d5f69b60d"
    },
    {
      "userFriendlyName": "FALL_WATER_1",
      "uName": "MR_RD_WFAL_02_01_Amb.ny.32.dspadpcm",
      "dxName": "pVO_MR_FALL_WATER",
      "bfwavFileSize": "11712",
      "checksumMD5": "4cfa19c3b7c7961866f3d1c571595efb"
    },
    {
      "userFriendlyName": "FALL_WATER_2",
      "uName": "MR_RD_WFAL_02_06_Amb.ny.32.dspadpcm",
      "dxName": "pVO_MR_FALL_WATER_END",
      "bfwavFileSize": "14256",
      "checksumMD5": "a8ee7843f49838c0c4a939f079d95ca7"
    },
    {
      "userFriendlyName": "FINISH_GOOD_2",
      "uName": "mr_Result_1st-08_Amb.ny.32.dspadpcm",
      "dxName": "pVO_MR_GOL_GOD2",
      "bfwavFileSize": "23896",
      "checksumMD5": "7dca49c1d6b570fb1e8093c4cfb5fd7f"
    },
    {
      "userFriendlyName": "SFX_HORN_OFF",
      "uName": "pSE_HORN_MARIO_OFF.dspadpcm",
      "dxName": "pSE_HORN_MARIO_OFF",
      "bfwavFileSize": "4120",
      "checksumMD5": "475dc451f441b3b06ed19d1241a7dce8"
    },
    {
      "userFriendlyName": "SFX_HORN_ON",
      "uName": "pSE_HORN_MARIO_ON.dspadpcm",
      "dxName": "pSE_HORN_MARIO_ON",
      "bfwavFileSize": "13032",
      "checksumMD5": "2d537d9b13663212f3a9d92b4f27ef93"
    },
    {
      "userFriendlyName": "SFX_ITEM_HORN",
      "uName": "pSE_HORN_MARIO_ON_SP.dspadpcm",
      "dxName": "pSE_HORN_MARIO_ON_SP",
      "bfwavFileSize": "21616",
      "checksumMD5": "2c4642abd7886a6be3d0521af5a3b468"
    },
    {
      "userFriendlyName": "SELECT_DRIVER",
      "uName": "pVO_M_MR_SELECT_CHAR.dspadpcm",
      "dxName": "pVO_M_MR_SELECT_CHAR",
      "bfwavFileSize": "30600",
      "checksumMD5": "1720ff40d2e781e1821cf30fd9e1d7c0"
    }
  ]
}